README.rst
setup.py
kiga_plugin/__init__.py
kiga_plugin.egg-info/PKG-INFO
kiga_plugin.egg-info/SOURCES.txt
kiga_plugin.egg-info/dependency_links.txt
kiga_plugin.egg-info/top_level.txt