Metadata-Version: 1.1
Name: kiga_plugin
Version: 0.0.1
Summary: plugin loader using pkg_resources.
Home-page: https://github.com/xica/kiga-plugin
Author: xica development team
Author-email: info@xica.net
License: MIT
Platform: UNKNOWN
Classifier: Development Status :: 3 - Alpha
Classifier: Environment :: Web Environment
Classifier: Intended Audience :: Developers
Classifier: License :: OSI Approved :: MIT License
Classifier: Operating System :: POSIX :: Linux
Classifier: Programming Language :: Python
